jk_exceptionhelper/ExceptionObject.py
jk_exceptionhelper/StackTraceItem.py
jk_exceptionhelper/StackTraceProcessor.py
jk_exceptionhelper/__init__.py
jk_exceptionhelper/exception_helper.py
jk_exceptionhelper-0.2025.5.17.dist-info/WHEEL
jk_exceptionhelper-0.2025.5.17.dist-info/METADATA
jk_exceptionhelper-0.2025.5.17.dist-info/RECORD
