Metadata-Version: 2.1
Name: jk_exceptionhelper
Version: 0.2025.5.17
Summary: As the python exception API is quite a bit obscure this python module wraps around python exceptions to provide a clean interface for analysis and logging purposes.
Keywords: exception handling,debugging
Author-email: Jürgen Knauth <pubsrc@binary-overflow.de>
Maintainer-email: Jürgen Knauth <pubsrc@binary-overflow.de>
Requires-Python: >=3.8
Classifier: Development Status :: 5 - Production/Stable
Classifier: License :: OSI Approved :: Apache Software License
Classifier: Programming Language :: Python :: 3
Classifier: Topic :: Software Development :: Testing
